[
  {
    "id": "recompile_limit",
    "name": "recompile_limit",
    "description": "Maximum number of recompilations before dynamo gives up on a frame (default: 8)",
    "aliases": [
      "cache_size_limit",
      "TORCHDYNAMO_RECOMPILE_LIMIT"
    ],
    "validation": {
      "status": "confirmed",
      "validated_date": "2026-04-14"
    },
    "freshness": {
      "status": "living",
      "reason": "Confirmed in source (2026-04-14)",
      "classified_date": "2026-04-14"
    }
  },
  {
    "id": "accumulated_recompile_limit",
    "name": "accumulated_recompile_limit",
    "description": "Safeguard to prevent horrible recompilations across all frames (default: 256)",
    "aliases": [
      "accumulated_cache_size_limit"
    ],
    "validation": {
      "status": "confirmed",
      "validated_date": "2026-04-14"
    },
    "freshness": {
      "status": "living",
      "reason": "Confirmed in source (2026-04-14)",
      "classified_date": "2026-04-14"
    }
  },
  {
    "id": "capture_scalar_outputs",
    "name": "capture_scalar_outputs",
    "description": "Capture scalar outputs (e.g., from .item()) in the graph instead of graph breaking (requires dynamic_shapes)",
    "aliases": [
      "TORCHDYNAMO_CAPTURE_SCALAR_OUTPUTS"
    ],
    "validation": {
      "status": "confirmed",
      "validated_date": "2026-04-14"
    },
    "freshness": {
      "status": "living",
      "reason": "Confirmed in source (2026-04-14)",
      "classified_date": "2026-04-14"
    }
  },
  {
    "id": "capture_dynamic_output_shape_ops",
    "name": "capture_dynamic_output_shape_ops",
    "description": "Capture ops with dynamic output shapes (nonzero, unique) instead of graph breaking",
    "aliases": [
      "TORCHDYNAMO_CAPTURE_DYNAMIC_OUTPUT_SHAPE_OPS"
    ],
    "validation": {
      "status": "confirmed",
      "validated_date": "2026-04-14"
    },
    "freshness": {
      "status": "living",
      "reason": "Confirmed in source (2026-04-14)",
      "classified_date": "2026-04-14"
    }
  },
  {
    "id": "suppress_errors",
    "name": "suppress_errors",
    "description": "Suppress errors in torch._dynamo.optimize and force fallback to eager (may lose optimization opportunities)",
    "aliases": [
      "TORCHDYNAMO_SUPPRESS_ERRORS"
    ],
    "validation": {
      "status": "confirmed",
      "validated_date": "2026-04-14"
    },
    "freshness": {
      "status": "living",
      "reason": "Confirmed in source (2026-04-14)",
      "classified_date": "2026-04-14"
    }
  },
  {
    "id": "inline_inbuilt_nn_modules",
    "name": "inline_inbuilt_nn_modules",
    "description": "Inline built-in nn modules for regional compilation (deprecated: always True, 27% compile time reduction)",
    "aliases": [
      "TORCHDYNAMO_INLINE_INBUILT_NN_MODULES"
    ],
    "validation": {
      "status": "confirmed",
      "validated_date": "2026-04-14"
    },
    "freshness": {
      "status": "living",
      "reason": "Confirmed in source (2026-04-14)",
      "classified_date": "2026-04-14"
    }
  },
  {
    "id": "verbose",
    "name": "verbose",
    "description": "Print full stack traces on warnings and errors for debugging",
    "aliases": [
      "TORCHDYNAMO_VERBOSE"
    ],
    "validation": {
      "status": "confirmed",
      "validated_date": "2026-04-14"
    },
    "freshness": {
      "status": "living",
      "reason": "Confirmed in source (2026-04-14)",
      "classified_date": "2026-04-14"
    }
  },
  {
    "id": "repro_level",
    "name": "repro_level",
    "description": "Compiler debug info level: 1=dumps original graph on fail, 2=minifier launcher, 3=always minifier, 4=accuracy fails (default: 2)",
    "aliases": [
      "TORCHDYNAMO_REPRO_LEVEL"
    ],
    "validation": {
      "status": "confirmed",
      "validated_date": "2026-04-14"
    },
    "freshness": {
      "status": "living",
      "reason": "Confirmed in source (2026-04-14)",
      "classified_date": "2026-04-14"
    }
  },
  {
    "id": "repro_after",
    "name": "repro_after",
    "description": "Run minifier at specific stage: None=off, 'dynamo'=TorchDynamo graphs, 'aot'=AOT Autograd graphs",
    "aliases": [
      "TORCHDYNAMO_REPRO_AFTER"
    ],
    "validation": {
      "status": "confirmed",
      "validated_date": "2026-04-14"
    },
    "freshness": {
      "status": "living",
      "reason": "Confirmed in source (2026-04-14)",
      "classified_date": "2026-04-14"
    }
  },
  {
    "id": "torch_logs",
    "name": "TORCH_LOGS",
    "description": "Configure logging for dynamo, aot, inductor (e.g., TORCH_LOGS=\"dynamo,aot,inductor\" or TORCH_LOGS=\"graph_breaks\")",
    "aliases": [
      "torch._logging.set_logs"
    ],
    "validation": {
      "status": "confirmed",
      "validated_date": "2026-04-14"
    },
    "freshness": {
      "status": "living",
      "reason": "Confirmed in source (2026-04-14)",
      "classified_date": "2026-04-14"
    }
  },
  {
    "id": "torch_compile_debug",
    "name": "TORCH_COMPILE_DEBUG",
    "description": "Enable detailed inductor debug output and trace logging",
    "validation": {
      "status": "confirmed",
      "validated_date": "2026-04-14"
    },
    "freshness": {
      "status": "living",
      "reason": "Confirmed in source (2026-04-14)",
      "classified_date": "2026-04-14"
    }
  },
  {
    "id": "specialize_int",
    "name": "specialize_int",
    "description": "Specialize on int inputs when dynamic_shapes is True (default: False, mostly for export)",
    "validation": {
      "status": "confirmed",
      "validated_date": "2026-04-14"
    },
    "freshness": {
      "status": "living",
      "reason": "Confirmed in source (2026-04-14)",
      "classified_date": "2026-04-14"
    }
  },
  {
    "id": "specialize_float",
    "name": "specialize_float",
    "description": "Specialize on float inputs (default: False, backends inconsistently support float codegen)",
    "validation": {
      "status": "confirmed",
      "validated_date": "2026-04-14"
    },
    "freshness": {
      "status": "living",
      "reason": "Confirmed in source (2026-04-14)",
      "classified_date": "2026-04-14"
    }
  },
  {
    "id": "assume_static_by_default",
    "name": "assume_static_by_default",
    "description": "Only allocate symbols for shapes marked dynamic via mark_dynamic (default: True)",
    "validation": {
      "status": "confirmed",
      "validated_date": "2026-04-14"
    },
    "freshness": {
      "status": "living",
      "reason": "Confirmed in source (2026-04-14)",
      "classified_date": "2026-04-14"
    }
  },
  {
    "id": "guard_nn_modules",
    "name": "guard_nn_modules",
    "description": "Assume nn.Module contents are mutable and add guards (default: True, opposite of freezing)",
    "validation": {
      "status": "confirmed",
      "validated_date": "2026-04-14"
    },
    "freshness": {
      "status": "living",
      "reason": "Confirmed in source (2026-04-14)",
      "classified_date": "2026-04-14"
    }
  },
  {
    "id": "optimize_ddp",
    "name": "optimize_ddp",
    "description": "Optimize DDP module: 'ddp_optimizer' (split graph for overlap), 'python_reducer', 'no_optimization' (default: ddp_optimizer)",
    "validation": {
      "status": "confirmed",
      "validated_date": "2026-04-14"
    },
    "freshness": {
      "status": "living",
      "reason": "Confirmed in source (2026-04-14)",
      "classified_date": "2026-04-14"
    }
  },
  {
    "id": "allow_rnn",
    "name": "allow_rnn",
    "description": "Disable graph breaking on RNN ops (YMMV with backends, default: False)",
    "validation": {
      "status": "confirmed",
      "validated_date": "2026-04-14"
    },
    "freshness": {
      "status": "living",
      "reason": "Confirmed in source (2026-04-14)",
      "classified_date": "2026-04-14"
    }
  },
  {
    "id": "trace_numpy",
    "name": "trace_numpy",
    "description": "Trace through NumPy operations instead of graph breaking (default: True)",
    "validation": {
      "status": "confirmed",
      "validated_date": "2026-04-14"
    },
    "freshness": {
      "status": "living",
      "reason": "Confirmed in source (2026-04-14)",
      "classified_date": "2026-04-14"
    }
  },
  {
    "id": "enable_compiler_collectives",
    "name": "enable_compiler_collectives",
    "description": "Use collectives during compilation to sync dynamic shape decisions across ranks (requires SPMD, prevents NCCL hangs)",
    "aliases": [
      "TORCH_COMPILER_COLLECTIVES"
    ],
    "validation": {
      "status": "confirmed",
      "validated_date": "2026-04-14"
    },
    "freshness": {
      "status": "living",
      "reason": "Confirmed in source (2026-04-14)",
      "classified_date": "2026-04-14"
    }
  },
  {
    "id": "torch_compile_dynamic_sources",
    "name": "TORCH_COMPILE_DYNAMIC_SOURCES",
    "description": "Specify dynamic inputs upfront (e.g., L['x'],L['y']) to reduce compile time, 'mandatory' for performance",
    "validation": {
      "status": "confirmed",
      "validated_date": "2026-04-14"
    },
    "freshness": {
      "status": "living",
      "reason": "Confirmed in source (2026-04-14)",
      "classified_date": "2026-04-14"
    }
  },
  {
    "id": "max_autotune_gemm",
    "name": "max_autotune_gemm",
    "description": "Enable slow autotuning for GEMM operations only (default: False)",
    "aliases": [
      "TORCHINDUCTOR_MAX_AUTOTUNE_GEMM"
    ],
    "validation": {
      "status": "confirmed",
      "validated_date": "2026-04-14"
    },
    "freshness": {
      "status": "living",
      "reason": "Confirmed in source (2026-04-14)",
      "classified_date": "2026-04-14"
    }
  },
  {
    "id": "fallback_random",
    "name": "fallback_random",
    "description": "Fallback to eager for random/dropout ops (slow but useful for debugging, default: False)",
    "validation": {
      "status": "confirmed",
      "validated_date": "2026-04-14"
    },
    "freshness": {
      "status": "living",
      "reason": "Confirmed in source (2026-04-14)",
      "classified_date": "2026-04-14"
    }
  },
  {
    "id": "force_disable_caches",
    "name": "force_disable_caches",
    "description": "Disable all caching mechanisms (fx_graph_cache, autotune_cache) for debugging",
    "aliases": [
      "TORCHINDUCTOR_FORCE_DISABLE_CACHES"
    ],
    "validation": {
      "status": "confirmed",
      "validated_date": "2026-04-14"
    },
    "freshness": {
      "status": "living",
      "reason": "Confirmed in source (2026-04-14)",
      "classified_date": "2026-04-14"
    }
  },
  {
    "id": "cpp_wrapper",
    "name": "cpp_wrapper",
    "description": "Use C++ wrapper instead of Python wrapper for inductor (incompatible with disable_cpp_codegen)",
    "aliases": [
      "TORCHINDUCTOR_CPP_WRAPPER"
    ],
    "validation": {
      "status": "confirmed",
      "validated_date": "2026-04-14"
    },
    "freshness": {
      "status": "living",
      "reason": "Confirmed in source (2026-04-14)",
      "classified_date": "2026-04-14"
    }
  },
  {
    "id": "fx_graph_cache",
    "name": "fx_graph_cache",
    "description": "Use FX AOT graph codegen cache to speed up compilation (default: True)",
    "aliases": [
      "TORCHINDUCTOR_FX_GRAPH_CACHE"
    ],
    "validation": {
      "status": "confirmed",
      "validated_date": "2026-04-14"
    },
    "freshness": {
      "status": "living",
      "reason": "Confirmed in source (2026-04-14)",
      "classified_date": "2026-04-14"
    }
  },
  {
    "id": "emulate_precision_casts",
    "name": "emulate_precision_casts",
    "description": "Emulate precision casts in inductor to match eager mode numerics",
    "aliases": [
      "TORCHINDUCTOR_EMULATE_PRECISION_CASTS"
    ],
    "validation": {
      "status": "confirmed",
      "validated_date": "2026-04-14"
    },
    "freshness": {
      "status": "living",
      "reason": "Confirmed in source (2026-04-14)",
      "classified_date": "2026-04-14"
    }
  },
  {
    "id": "dynamic_shapes_flag",
    "name": "dynamic",
    "description": "torch.compile flag to enable dynamic shapes (dynamic=True) or force static shapes (dynamic=False)",
    "validation": {
      "status": "confirmed",
      "validated_date": "2026-04-14"
    },
    "freshness": {
      "status": "living",
      "reason": "Confirmed in source (2026-04-14)",
      "classified_date": "2026-04-14"
    }
  },
  {
    "id": "fullgraph_flag",
    "name": "fullgraph",
    "description": "torch.compile flag to require no graph breaks (fullgraph=True) or allow them (fullgraph=False)",
    "validation": {
      "status": "confirmed",
      "validated_date": "2026-04-14"
    },
    "freshness": {
      "status": "living",
      "reason": "Confirmed in source (2026-04-14)",
      "classified_date": "2026-04-14"
    }
  },
  {
    "id": "max_autotune",
    "name": "max_autotune",
    "description": "Try all kernel options including Triton templates for matmul/conv. May not help if 64-bit indexing not implemented for templates.",
    "aliases": [
      "TORCHINDUCTOR_MAX_AUTOTUNE"
    ],
    "validation": {
      "status": "confirmed",
      "validated_date": "2026-04-14"
    },
    "freshness": {
      "status": "living",
      "reason": "Confirmed in source (2026-04-14)",
      "classified_date": "2026-04-14"
    }
  },
  {
    "id": "triton_cudagraphs",
    "name": "triton.cudagraphs",
    "description": "Enable/disable CUDA graph capture for Triton kernels (disable for GPU compatibility testing or debugging)",
    "aliases": [
      "torch._inductor.config.triton.cudagraphs"
    ],
    "validation": {
      "status": "confirmed",
      "validated_date": "2026-04-14"
    },
    "freshness": {
      "status": "living",
      "reason": "Confirmed in source (2026-04-14)",
      "classified_date": "2026-04-14"
    }
  },
  {
    "id": "aot_fx_graphs",
    "name": "aot_graphs",
    "description": "Log AOT Autograd forward/backward graphs. Legacy env var AOT_FX_GRAPHS still works in some internal code.",
    "aliases": [
      "AOT_FX_GRAPHS",
      "torch._functorch.config.aot_graphs"
    ],
    "validation": {
      "status": "confirmed",
      "validated_date": "2026-04-14"
    },
    "freshness": {
      "status": "living",
      "reason": "Confirmed in source (2026-04-14)",
      "classified_date": "2026-04-14"
    }
  },
  {
    "id": "fake_tensor_crossref",
    "name": "fake_tensor_crossref",
    "description": "Cross-reference fake tensor metadata against concrete tensors to detect stride/shape mismatches. Set to 'all' to check all ops.",
    "aliases": [
      "torch._functorch.config.fake_tensor_crossref"
    ],
    "validation": {
      "status": "confirmed",
      "validated_date": "2026-04-14"
    },
    "freshness": {
      "status": "living",
      "reason": "Confirmed in source (2026-04-14)",
      "classified_date": "2026-04-14"
    }
  },
  {
    "id": "use_duck_shape",
    "name": "use_duck_shape",
    "description": "torch.fx.experimental._config.use_duck_shape \u2014 when True (default), dimensions with same value at first compile are assumed equal, causing recompilation when they differ later",
    "evidence_issues": [
      150702
    ],
    "temporal": {
      "first_seen_date": "2025-04-04",
      "last_seen_date": "2025-04-15",
      "first_seen_version": "2.6",
      "last_seen_version": "2.7",
      "has_open_evidence": false
    },
    "freshness": {
      "status": "living",
      "reason": "Active config, still default behavior",
      "classified_date": "2026-04-14"
    },
    "validation": {
      "status": "confirmed",
      "validated_date": "2026-04-14",
      "location": "torch.fx.experimental._config.use_duck_shape"
    }
  },
  {
    "id": "TORCHDYNAMO_REPRO_IGNORE_NON_FP",
    "name": "TORCHDYNAMO_REPRO_IGNORE_NON_FP",
    "description": "Environment variable \u2014 when set to 1, skips accuracy checks on non-floating-point tensors (uint8, bool) to avoid false positives",
    "evidence_issues": [
      121069
    ],
    "temporal": {
      "first_seen_date": "2024-03-02",
      "last_seen_date": "2024-10-24",
      "first_seen_version": "2.2",
      "last_seen_version": "2.4",
      "has_open_evidence": false
    },
    "freshness": {
      "status": "living",
      "reason": "Diagnostic config \u2014 always available",
      "classified_date": "2026-04-14"
    },
    "validation": {
      "status": "confirmed",
      "validated_date": "2026-04-14",
      "location": "torch._dynamo.config.repro_ignore_non_fp"
    }
  },
  {
    "id": "TORCHINDUCTOR_ABI_COMPATIBLE",
    "name": "TORCHINDUCTOR_ABI_COMPATIBLE",
    "description": "Environment variable \u2014 when set to 1, enables ABI-compatible compilation mode for AOTInductor, intended for cross-version model loading (still maturing)",
    "evidence_issues": [
      123745
    ],
    "temporal": {
      "first_seen_date": "2024-04-07",
      "last_seen_date": "2024-11-08",
      "first_seen_version": "2.3",
      "last_seen_version": "2.5",
      "has_open_evidence": false
    },
    "freshness": {
      "status": "living",
      "reason": "Active feature, still being developed",
      "classified_date": "2026-04-14"
    },
    "validation": {
      "status": "confirmed",
      "validated_date": "2026-04-14",
      "location": "torch._inductor abi_compatible mode"
    }
  },
  {
    "id": "TORCH_COMPILE_DEBUG_DIR",
    "name": "TORCH_COMPILE_DEBUG_DIR",
    "description": "Environment variable \u2014 directory for torch.compile debug output (generated code, graphs, timing)",
    "evidence_issues": [
      100086
    ],
    "freshness": {
      "status": "living",
      "reason": "Active diagnostic config",
      "classified_date": "2026-04-14"
    },
    "validation": {
      "status": "confirmed",
      "validated_date": "2026-04-14"
    }
  },
  {
    "id": "TORCH_USE_CUDA_DSA",
    "name": "TORCH_USE_CUDA_DSA",
    "description": "Environment variable \u2014 enables CUDA Device-Side Assertions for better error messages on GPU errors",
    "evidence_issues": [
      95595
    ],
    "freshness": {
      "status": "living",
      "reason": "Active diagnostic config",
      "classified_date": "2026-04-14"
    },
    "validation": {
      "status": "confirmed",
      "validated_date": "2026-04-14"
    }
  },
  {
    "id": "capture_autograd_function",
    "name": "capture_autograd_function",
    "description": "torch._dynamo.config.capture_autograd_function \u2014 enables tracing through custom autograd functions (torch.autograd.Function)",
    "evidence_issues": [
      109910
    ],
    "freshness": {
      "status": "living",
      "reason": "Active feature config",
      "classified_date": "2026-04-14"
    },
    "validation": {
      "status": "confirmed",
      "validated_date": "2026-04-14"
    }
  },
  {
    "id": "max_autotune_gemm_backends",
    "name": "max_autotune_gemm_backends",
    "description": "torch._inductor.config.max_autotune_gemm_backends \u2014 controls which GEMM backends are tried during max_autotune (ATEN, TRITON, CPP)",
    "evidence_issues": [
      125728
    ],
    "freshness": {
      "status": "living",
      "reason": "Active perf config",
      "classified_date": "2026-04-14"
    },
    "validation": {
      "status": "confirmed",
      "validated_date": "2026-04-14"
    }
  },
  {
    "id": "side_effect_replay_policy",
    "name": "side_effect_replay_policy",
    "description": "torch._dynamo.config.side_effect_replay_policy \u2014 controls how side effects (prints, logging) are replayed in compiled code",
    "evidence_issues": [
      166173
    ],
    "freshness": {
      "status": "living",
      "reason": "New config from PT 2.5+",
      "classified_date": "2026-04-14"
    },
    "validation": {
      "status": "confirmed",
      "validated_date": "2026-04-14"
    }
  }
]